rssfeeder/__init__.py
rssfeeder-0.1.1.dist-info/DESCRIPTION.rst
rssfeeder-0.1.1.dist-info/METADATA
rssfeeder-0.1.1.dist-info/RECORD
rssfeeder-0.1.1.dist-info/WHEEL
rssfeeder-0.1.1.dist-info/metadata.json
rssfeeder-0.1.1.dist-info/top_level.txt
