Metadata-Version: 2.0
Name: rssfeeder
Version: 0.1.1
Summary: A library to read RSS feeds and post to different destinations.
Home-page: https://github.com/ozgurakan/rssfeeder
Author: Oz Akan
Author-email: oz@akan.me
License: UNKNOWN
Keywords: rss,feed,aws,dynamodb
Platform: UNKNOWN
Requires-Python: >=3
Requires-Dist: boto3
Requires-Dist: feedparser
